{
    "Concept": "Absurd Faith",
    "Category": "Philosophy Concepts",
    "Author": [
        "Søren Kierkegaard"
    ],
    "Antagonist": "Rational Theodicy",
    "Keywords": [
        "faith"
        , "absurd"
        , "paradox"
        , "religion"
        , "Absurd Faith"
        , "Existentialism"
        , "Religion"
        , "Kierkegaard"
    ],
    "Content": "For Kierkegaard, true faith embraces the absurd—paradoxes like God becoming man. Rather than seeking rational harmony, faith finds its strength in embracing the incomprehensible."
  }