{
    "Concept": "Cultural Relativism",
    "Category": "Philosophy Concepts",
    "Author": ["Franz Boas", "John Stuart Mill"],
    "Antagonist": "Moral Universalism",
    "Keywords": [
        "relativism"
        , "culture"
        , "morality"
        , "diversity"
        , "Ethics"
    ],
    "Content": "Cultural relativism holds that moral values and truths are relative to cultural context and cannot be judged by external standards. Critics argue that this view makes it difficult to condemn harmful practices across cultures."
  }