{
    "Concept": "Moral Luck",
    "Category": "Philosophy Concepts",
    "Author": ["Thomas Nagel", "Bernard Williams"],
    "Antagonist": "Strict Moral Responsibility",
    "Keywords": [
        "Moral"
        , "Luck"
        , "Thomas Nagel"
        , "Bernard Williams"
        , "Ethics"
        , "Moral"
        , "Responsibility"
    ],
    "Content": "Moral luck refers to cases where factors beyond a person’s control affect moral judgment of their actions. It challenges the idea that morality depends solely on intent rather than circumstance."
  }