{
    "Concept": "Zombie Argument",
    "Category": "Philosophy Concepts",
    "Author": ["David Chalmers"],
    "Antagonist": "Physicalism",
    "Keywords": [
        "Zombie Argument"
        , "David Chalmers"
        , "Physicalism"
        , "consciousness"
        , "zombies"
        , "mind-body"
        , "qualia"
    ],
    "Content": "The zombie argument imagines beings physically identical to humans but lacking consciousness. Chalmers uses it to argue that physicalism cannot fully explain subjective experience or qualia."
  }